[
{"id":"1","firstName":"Reggie","lastName":"Acum","identification":"8764463707","mobile":"986255917","secondMobile":"970299362","tariff":"Particular","civil":"Viudo/a","birthDate":"01/09/2021","creationDate":"Wed Apr 26 2022 18:07:19 GMT-0500 (hora de Ecuador)","address":"Coda","email":"nmillbank0@google.ru","firstNameSpouse":"Jolynn","lastNameSpouse":"Vassar","identificationSpouse":"7813054787","mobileSpouse":"958346907","relationShip":"Hija","firstNameRelationShip":"Nikkie","lastNameRelationShip":"Millbank","mobileRelationShip":"1465243942","savingBalance":"1826","creditBalance":"1921"}
,
{"id":"2","firstName":"Gerardo","lastName":"Reford","identification":"4969774569","mobile":"969235283","secondMobile":"925328645","tariff":"Particular","civil":"Soltero/a","birthDate":"04/11/2021","creationDate":"26/06/2019","address":"Jalgung","email":"omalkin1@comsenz.com","firstNameSpouse":"Ailsun","lastNameSpouse":"Naismith","identificationSpouse":"72954192","mobileSpouse":"922635089","relationShip":"Amigo","firstNameRelationShip":"Orelee","lastNameRelationShip":"Malkin","mobileRelationShip":"1530752615","savingBalance":"1923","creditBalance":"301"},
{"id":"3","firstName":"Theo","lastName":"McSharry","identification":"2159355933","mobile":"943690176","secondMobile":"956944439","tariff":"Socio","civil":"Soltero/a","birthDate":"27/06/2021","creationDate":"30/09/2019","address":"Zhongguan","email":"aomolan2@vinaora.com","firstNameSpouse":"Alverta","lastNameSpouse":"Eberdt","identificationSpouse":"8240640449","mobileSpouse":"907413492","relationShip":"Hija","firstNameRelationShip":"Alyssa","lastNameRelationShip":"O' Molan","mobileRelationShip":"427040876","savingBalance":"1907","creditBalance":"517"},
{"id":"4","firstName":"Luella","lastName":"Ladlow","identification":"5770162758","mobile":"936044490","secondMobile":"994697106","tariff":"Socio","civil":"Soltero/a","birthDate":"17/09/2021","creationDate":"09/01/2022","address":"Frutal","email":"sbiggs3@army.mil","firstNameSpouse":"Eddy","lastNameSpouse":"Denge","identificationSpouse":"9310366113","mobileSpouse":"911663618","relationShip":"Amigo","firstNameRelationShip":"Stevy","lastNameRelationShip":"Biggs","mobileRelationShip":"9819901669","savingBalance":"1126","creditBalance":"617"},
{"id":"5","firstName":"Sallee","lastName":"Oylett","identification":"68084934","mobile":"914417201","secondMobile":"929670159","tariff":"Socio","civil":"Union Libre","birthDate":"16/04/2022","creationDate":"14/11/2019","address":"Tessalit","email":"ksappson4@ocn.ne.jp","firstNameSpouse":"Freeland","lastNameSpouse":"Mate","identificationSpouse":"4050914938","mobileSpouse":"948564998","relationShip":"Prima","firstNameRelationShip":"Kate","lastNameRelationShip":"Sappson","mobileRelationShip":"1799967621","savingBalance":"1920","creditBalance":"865"}
,
{"id":"6","firstName":"Tammie","lastName":"Jovis","identification":"5097747611","mobile":"907485752","secondMobile":"940205532","tariff":"Socio","civil":"Casado/a","birthDate":"22/07/2021","creationDate":"30/11/2021","address":"El Aguacate","email":"kfrancescuzzi5@wp.com","firstNameSpouse":"Magnum","lastNameSpouse":"Foucar","identificationSpouse":"6415177320","mobileSpouse":"992188337","relationShip":"Madre","firstNameRelationShip":"Karrah","lastNameRelationShip":"Francescuzzi","mobileRelationShip":"7132949588","savingBalance":"241","creditBalance":"1731"},
{"id":"7","firstName":"Hershel","lastName":"McGarel","identification":"4248519780","mobile":"906176277","secondMobile":"961686891","tariff":"Socio","civil":"Soltero/a","birthDate":"02/06/2021","creationDate":"23/12/2019","address":"Naa Santa","email":"jcrooke6@arizona.edu","firstNameSpouse":"Shannen","lastNameSpouse":"Rapi","identificationSpouse":"4820227840","mobileSpouse":"965142745","relationShip":"Amigo","firstNameRelationShip":"Jeanne","lastNameRelationShip":"Crooke","mobileRelationShip":"7968492358","savingBalance":"889","creditBalance":"450"}
,
{"id":"8","firstName":"Johnath","lastName":"Cornelis","identification":"2882415714","mobile":"978599785","secondMobile":"933459460","tariff":"Particular","civil":"Soltero/a","birthDate":"23/12/2021","creationDate":"29/12/2021","address":"Jeruk","email":"cpeaddie7@economist.com","firstNameSpouse":"Carr","lastNameSpouse":"Augustin","identificationSpouse":"6370915135","mobileSpouse":"999163447","relationShip":"Padre","firstNameRelationShip":"Candide","lastNameRelationShip":"Peaddie","mobileRelationShip":"4334600135","savingBalance":"1520","creditBalance":"1354"},
{"id":"9","firstName":"Julie","lastName":"Bullus","identification":"1539554413","mobile":"979166598","secondMobile":"931760463","tariff":"Particular","civil":"Casado/a","birthDate":"15/09/2021","creationDate":"29/07/2021","address":"Longford","email":"jgarvagh8@delicious.com","firstNameSpouse":"Chery","lastNameSpouse":"Ovill","identificationSpouse":"1376569463","mobileSpouse":"917554471","relationShip":"Taa","firstNameRelationShip":"Jemmy","lastNameRelationShip":"Garvagh","mobileRelationShip":"3862388548","savingBalance":"661","creditBalance":"54"}
,
{"id":"10","firstName":"Bunny","lastName":"Edge","identification":"3156195723","mobile":"948956289","secondMobile":"990771663","tariff":"Particular","civil":"Casado/a","birthDate":"18/11/2021","creationDate":"04/03/2021","address":"Jamaica","email":"rklimczak9@zdnet.com","firstNameSpouse":"Peyter","lastNameSpouse":"Theodoris","identificationSpouse":"4635411260","mobileSpouse":"910834029","relationShip":"Amigo","firstNameRelationShip":"Robinet","lastNameRelationShip":"Klimczak","mobileRelationShip":"985233042","savingBalance":"73","creditBalance":"363"},
{"id":"11","firstName":"Orelie","lastName":"Neylon","identification":"421396615","mobile":"960627155","secondMobile":"955118846","tariff":"Particular","civil":"Viudo/a","birthDate":"24/04/2021","creationDate":"28/11/2020","address":"Qingyun","email":"malsinaa@columbia.edu","firstNameSpouse":"Jobyna","lastNameSpouse":"Stoakes","identificationSpouse":"631320643","mobileSpouse":"996986979","relationShip":"Taa","firstNameRelationShip":"Myrtie","lastNameRelationShip":"Alsina","mobileRelationShip":"940456733","savingBalance":"546","creditBalance":"261"}
,
{"id":"12","firstName":"Denna","lastName":"Dempster","identification":"2084935454","mobile":"937679663","secondMobile":"923474060","tariff":"Particular","civil":"Casado/a","birthDate":"24/01/2022","creationDate":"22/09/2020","address":"Kembangan","email":"tcaushb@bbc.co.uk","firstNameSpouse":"Pat","lastNameSpouse":"Bradick","identificationSpouse":"1611003156","mobileSpouse":"957747224","relationShip":"Hija","firstNameRelationShip":"Theda","lastNameRelationShip":"Caush","mobileRelationShip":"9601500335","savingBalance":"528","creditBalance":"449"},
{"id":"13","firstName":"Susann","lastName":"Sebrens","identification":"7751971856","mobile":"900647719","secondMobile":"954683167","tariff":"Particular","civil":"Casado/a","birthDate":"18/11/2021","creationDate":"17/06/2020","address":"Kvasice","email":"kcinavasc@blogger.com","firstNameSpouse":"Cariotta","lastNameSpouse":"Wyse","identificationSpouse":"7140117955","mobileSpouse":"947050068","relationShip":"Amigo","firstNameRelationShip":"Karel","lastNameRelationShip":"Cinavas","mobileRelationShip":"6050151234","savingBalance":"1587","creditBalance":"1528"},
{"id":"14","firstName":"Karoline","lastName":"Coen","identification":"1543751878","mobile":"976889281","secondMobile":"995547832","tariff":"Socio","civil":"Soltero/a","birthDate":"30/12/2021","creationDate":"12/02/2022","address":"Nanyang","email":"kchoupind@scribd.com","firstNameSpouse":"Carmelle","lastNameSpouse":"Haime","identificationSpouse":"9237406025","mobileSpouse":"957430816","relationShip":"Hijo","firstNameRelationShip":"Kellyann","lastNameRelationShip":"Choupin","mobileRelationShip":"5797242613","savingBalance":"1847","creditBalance":"510"},
{"id":"15","firstName":"Paolo","lastName":"Stenton","identification":"4349852961","mobile":"922344518","secondMobile":"981764281","tariff":"Particular","civil":"Soltero/a","birthDate":"08/10/2021","creationDate":"03/07/2021","address":"Peso da Ragua","email":"lsenioure@cdc.gov","firstNameSpouse":"Solly","lastNameSpouse":"Habishaw","identificationSpouse":"1292714001","mobileSpouse":"929446168","relationShip":"Padre","firstNameRelationShip":"Lacey","lastNameRelationShip":"Seniour","mobileRelationShip":"3494043109","savingBalance":"288","creditBalance":"1319"}
,
{"id":"16","firstName":"Gus","lastName":"Keenlyside","identification":"5941841661","mobile":"911744116","secondMobile":"949338828","tariff":"Socio","civil":"Union Libre","birthDate":"23/12/2021","creationDate":"06/04/2021","address":"Sishui","email":"bdomenicif@mapy.cz","firstNameSpouse":"Bobina","lastNameSpouse":"Stucke","identificationSpouse":"9732247638","mobileSpouse":"970939811","relationShip":"Prima","firstNameRelationShip":"Barthel","lastNameRelationShip":"Domenici","mobileRelationShip":"9998354911","savingBalance":"1640","creditBalance":"522"}
,
{"id":"17","firstName":"Cly","lastName":"Freeburn","identification":"968557088","mobile":"915040681","secondMobile":"976357378","tariff":"Socio","civil":"Casado/a","birthDate":"29/03/2022","creationDate":"28/11/2020","address":"Chase","email":"pdassindaleg@reverbnation.com","firstNameSpouse":"Kandy","lastNameSpouse":"Cumming","identificationSpouse":"3028148395","mobileSpouse":"918627506","relationShip":"Padre","firstNameRelationShip":"Prent","lastNameRelationShip":"Dassindale","mobileRelationShip":"5860046627","savingBalance":"1323","creditBalance":"1375"},
{"id":"18","firstName":"Worth","lastName":"Folliss","identification":"1090077012","mobile":"926290803","secondMobile":"940175263","tariff":"Particular","civil":"Casado/a","birthDate":"25/11/2021","creationDate":"26/09/2019","address":"Paris 19","email":"csimmellh@prweb.com","firstNameSpouse":"Nestor","lastNameSpouse":"Thring","identificationSpouse":"3693766767","mobileSpouse":"984505648","relationShip":"Padre","firstNameRelationShip":"Carney","lastNameRelationShip":"Simmell","mobileRelationShip":"8758755010","savingBalance":"1419","creditBalance":"1231"},
{"id":"19","firstName":"Jareb","lastName":"Menego","identification":"8886646661","mobile":"936824342","secondMobile":"959667126","tariff":"Socio","civil":"Union Libre","birthDate":"18/11/2021","creationDate":"19/02/2021","address":"Sabbah","email":"mblakesleei@plala.or.jp","firstNameSpouse":"Leila","lastNameSpouse":"Thiolier","identificationSpouse":"8258549174","mobileSpouse":"978244632","relationShip":"Hijo","firstNameRelationShip":"Meagan","lastNameRelationShip":"Blakeslee","mobileRelationShip":"9914202550","savingBalance":"818","creditBalance":"784"}
,
{"id":"20","firstName":"Kalinda","lastName":"Hampshire","identification":"6524585266","mobile":"902646578","secondMobile":"936106965","tariff":"Particular","civil":"Union Libre","birthDate":"28/04/2021","creationDate":"22/03/2022","address":"El Calvario","email":"tstollwerkj@prlog.org","firstNameSpouse":"Leodora","lastNameSpouse":"Bissiker","identificationSpouse":"5441377186","mobileSpouse":"958923867","relationShip":"Padre","firstNameRelationShip":"Torry","lastNameRelationShip":"Stollwerk","mobileRelationShip":"9451645244","savingBalance":"787","creditBalance":"374"}
,
{"id":"21","firstName":"Antin","lastName":"Connold","identification":"2463428793","mobile":"999049017","secondMobile":"918155007","tariff":"Socio","civil":"Casado/a","birthDate":"02/06/2021","creationDate":"19/04/2020","address":"Mustvee","email":"bprobink@mtv.com","firstNameSpouse":"Ramonda","lastNameSpouse":"Prahm","identificationSpouse":"6292904895","mobileSpouse":"975585183","relationShip":"Padre","firstNameRelationShip":"Babbette","lastNameRelationShip":"Probin","mobileRelationShip":"4117618162","savingBalance":"591","creditBalance":"443"},
{"id":"22","firstName":"Guenevere","lastName":"Parmenter","identification":"2806267322","mobile":"982016807","secondMobile":"909561282","tariff":"Socio","civil":"Casado/a","birthDate":"26/04/2021","creationDate":"10/05/2021","address":"Roche Terre","email":"tsmyel@nature.com","firstNameSpouse":"Magdalen","lastNameSpouse":"Sones","identificationSpouse":"702650002","mobileSpouse":"973970104","relationShip":"Amiga","firstNameRelationShip":"Tadeas","lastNameRelationShip":"Smye","mobileRelationShip":"8229617925","savingBalance":"309","creditBalance":"1615"},
{"id":"23","firstName":"Osmund","lastName":"Fairfull","identification":"7674160362","mobile":"923353369","secondMobile":"927936621","tariff":"Particular","civil":"Casado/a","birthDate":"04/03/2022","creationDate":"20/06/2019","address":"Angoulame","email":"dretallackm@deviantart.com","firstNameSpouse":"Dayna","lastNameSpouse":"Hallgarth","identificationSpouse":"2795631245","mobileSpouse":"992313450","relationShip":"Primo","firstNameRelationShip":"Darlene","lastNameRelationShip":"Retallack","mobileRelationShip":"8660313004","savingBalance":"1986","creditBalance":"1006"}
,
{"id":"24","firstName":"Evy","lastName":"Melling","identification":"7624426960","mobile":"972667287","secondMobile":"934645622","tariff":"Particular","civil":"Viudo/a","birthDate":"08/01/2022","creationDate":"11/09/2020","address":"Laguilayan","email":"qchadbandn@tripod.com","firstNameSpouse":"Delly","lastNameSpouse":"de Merida","identificationSpouse":"6255070489","mobileSpouse":"904153161","relationShip":"Primo","firstNameRelationShip":"Quinlan","lastNameRelationShip":"Chadband","mobileRelationShip":"137659431","savingBalance":"1055","creditBalance":"196"},
{"id":"25","firstName":"Benn","lastName":"Benam","identification":"1318306151","mobile":"998957509","secondMobile":"933134743","tariff":"Socio","civil":"Viudo/a","birthDate":"21/09/2021","creationDate":"04/04/2020","address":"Krraba","email":"tschroedero@thetimes.co.uk","firstNameSpouse":"Gamaliel","lastNameSpouse":"Amberson","identificationSpouse":"1362232814","mobileSpouse":"952150100","relationShip":"Primo","firstNameRelationShip":"Tamma","lastNameRelationShip":"Schroeder","mobileRelationShip":"5034381726","savingBalance":"1838","creditBalance":"1592"}
,
{"id":"26","firstName":"Carie","lastName":"Muscat","identification":"6017356050","mobile":"992299232","secondMobile":"908254952","tariff":"Socio","civil":"Soltero/a","birthDate":"12/06/2021","creationDate":"13/02/2022","address":"Narva","email":"ajansenp@dagondesign.com","firstNameSpouse":"Angil","lastNameSpouse":"Meijer","identificationSpouse":"3644792426","mobileSpouse":"972581273","relationShip":"Tao","firstNameRelationShip":"Amitie","lastNameRelationShip":"Jansen","mobileRelationShip":"5047886860","savingBalance":"270","creditBalance":"810"}
,
{"id":"27","firstName":"Pammi","lastName":"Franzonetti","identification":"4131946604","mobile":"927528022","secondMobile":"945604982","tariff":"Particular","civil":"Viudo/a","birthDate":"15/07/2021","creationDate":"23/04/2021","address":"Isfahan","email":"gspeakmanq@unc.edu","firstNameSpouse":"Ammamaria","lastNameSpouse":"Mary","identificationSpouse":"7321846813","mobileSpouse":"980522792","relationShip":"Amigo","firstNameRelationShip":"Glory","lastNameRelationShip":"Speakman","mobileRelationShip":"8835277321","savingBalance":"684","creditBalance":"353"},
{"id":"28","firstName":"Darcey","lastName":"Gilphillan","identification":"2913762225","mobile":"924634715","secondMobile":"960282034","tariff":"Socio","civil":"Soltero/a","birthDate":"09/01/2022","creationDate":"26/11/2021","address":"Swan Hills","email":"rbartalotr@tamu.edu","firstNameSpouse":"Udale","lastNameSpouse":"Colbourn","identificationSpouse":"2507177336","mobileSpouse":"999423167","relationShip":"Madre","firstNameRelationShip":"Reagan","lastNameRelationShip":"Bartalot","mobileRelationShip":"3741739596","savingBalance":"974","creditBalance":"1884"},
{"id":"29","firstName":"Milicent","lastName":"Ulyet","identification":"3798503840","mobile":"970642012","secondMobile":"955530761","tariff":"Socio","civil":"Soltero/a","birthDate":"09/01/2022","creationDate":"11/04/2022","address":"Brodnica","email":"jgibletts@google.fr","firstNameSpouse":"Mirabel","lastNameSpouse":"Pasticznyk","identificationSpouse":"6448159109","mobileSpouse":"924281035","relationShip":"Madre","firstNameRelationShip":"Jo ann","lastNameRelationShip":"Giblett","mobileRelationShip":"8857782269","savingBalance":"1813","creditBalance":"97"},
{"id":"30","firstName":"Brandtr","lastName":"Lashley","identification":"6644833211","mobile":"995712741","secondMobile":"940054040","tariff":"Socio","civil":"Union Libre","birthDate":"28/11/2021","creationDate":"25/06/2020","address":"Grati Satu","email":"rglassardt@cocolog-nifty.com","firstNameSpouse":"Nathanael","lastNameSpouse":"Engledow","identificationSpouse":"2605229715","mobileSpouse":"913007559","relationShip":"Hijo","firstNameRelationShip":"Radcliffe","lastNameRelationShip":"Glassard","mobileRelationShip":"6397820538","savingBalance":"605","creditBalance":"1987"}
,
{"id":"31","firstName":"Currie","lastName":"Gunter","identification":"6349145454","mobile":"999881845","secondMobile":"914589386","tariff":"Particular","civil":"Soltero/a","birthDate":"20/06/2021","creationDate":"22/02/2021","address":"Shahrud","email":"abridglandu@twitter.com","firstNameSpouse":"Elijah","lastNameSpouse":"Shepley","identificationSpouse":"4949729260","mobileSpouse":"966359673","relationShip":"Hijo","firstNameRelationShip":"Anselma","lastNameRelationShip":"Bridgland","mobileRelationShip":"1046490189","savingBalance":"1637","creditBalance":"1991"},
{"id":"32","firstName":"Brietta","lastName":"Timcke","identification":"2741274317","mobile":"902596484","secondMobile":"959863496","tariff":"Socio","civil":"Viudo/a","birthDate":"30/12/2021","creationDate":"13/07/2019","address":"Periyiali","email":"amaccartneyv@buzzfeed.com","firstNameSpouse":"Fergus","lastNameSpouse":"Holdey","identificationSpouse":"7397170810","mobileSpouse":"973940958","relationShip":"Padre","firstNameRelationShip":"Ashby","lastNameRelationShip":"MacCartney","mobileRelationShip":"1730027661","savingBalance":"965","creditBalance":"329"}
,
{"id":"33","firstName":"Gerda","lastName":"Went","identification":"5308466550","mobile":"976059701","secondMobile":"917704044","tariff":"Particular","civil":"Union Libre","birthDate":"31/08/2021","creationDate":"10/03/2022","address":"Simitli","email":"lpurbrickw@devhub.com","firstNameSpouse":"Meg","lastNameSpouse":"Dobie","identificationSpouse":"1692076662","mobileSpouse":"954620250","relationShip":"Prima","firstNameRelationShip":"Lauree","lastNameRelationShip":"Purbrick","mobileRelationShip":"3803921823","savingBalance":"517","creditBalance":"1019"}
,
{"id":"34","firstName":"Beverlie","lastName":"Beaver","identification":"1297228868","mobile":"928547809","secondMobile":"939365184","tariff":"Socio","civil":"Casado/a","birthDate":"17/03/2022","creationDate":"25/07/2021","address":"Oytal","email":"nseviourx@bbc.co.uk","firstNameSpouse":"Addy","lastNameSpouse":"Agge","identificationSpouse":"3951264260","mobileSpouse":"930866402","relationShip":"Amigo","firstNameRelationShip":"Nelia","lastNameRelationShip":"Seviour","mobileRelationShip":"650007487","savingBalance":"166","creditBalance":"463"},
{"id":"35","firstName":"Janaya","lastName":"Gwilliams","identification":"5999074299","mobile":"967122722","secondMobile":"935729548","tariff":"Socio","civil":"Viudo/a","birthDate":"24/10/2021","creationDate":"26/11/2020","address":"Jiubao","email":"cghelerdiniy@mediafire.com","firstNameSpouse":"Carny","lastNameSpouse":"Goosey","identificationSpouse":"982909591","mobileSpouse":"958378072","relationShip":"Hija","firstNameRelationShip":"Candie","lastNameRelationShip":"Ghelerdini","mobileRelationShip":"4933242043","savingBalance":"1846","creditBalance":"1074"},
{"id":"36","firstName":"Elbert","lastName":"Mallia","identification":"7028535990","mobile":"950933823","secondMobile":"950998528","tariff":"Particular","civil":"Viudo/a","birthDate":"29/07/2021","creationDate":"29/10/2019","address":"Hongor","email":"drufflesz@wsj.com","firstNameSpouse":"Gayleen","lastNameSpouse":"Aires","identificationSpouse":"2928410704","mobileSpouse":"917950281","relationShip":"Primo","firstNameRelationShip":"Dean","lastNameRelationShip":"Ruffles","mobileRelationShip":"8082288305","savingBalance":"1340","creditBalance":"1202"},
{"id":"37","firstName":"Valencia","lastName":"Bunyard","identification":"7191674118","mobile":"931150484","secondMobile":"945640320","tariff":"Socio","civil":"Union Libre","birthDate":"02/03/2022","creationDate":"20/10/2019","address":"Luanshya","email":"djukubczak10@shareasale.com","firstNameSpouse":"Cody","lastNameSpouse":"Arbuckel","identificationSpouse":"5613104547","mobileSpouse":"999495086","relationShip":"Primo","firstNameRelationShip":"Darb","lastNameRelationShip":"Jukubczak","mobileRelationShip":"1870021117","savingBalance":"276","creditBalance":"1461"}
,
{"id":"38","firstName":"Jillene","lastName":"Laskey","identification":"8775507092","mobile":"971426174","secondMobile":"955351876","tariff":"Socio","civil":"Soltero/a","birthDate":"13/02/2022","creationDate":"27/01/2020","address":"Maluko","email":"ncheyenne11@vistaprint.com","firstNameSpouse":"Flinn","lastNameSpouse":"Drogan","identificationSpouse":"6611714834","mobileSpouse":"996415442","relationShip":"Hijo","firstNameRelationShip":"Nannie","lastNameRelationShip":"Cheyenne","mobileRelationShip":"3656886271","savingBalance":"1787","creditBalance":"384"},
{"id":"39","firstName":"Jordan","lastName":"Nowak","identification":"1461690388","mobile":"916846397","secondMobile":"954355541","tariff":"Socio","civil":"Soltero/a","birthDate":"18/10/2021","creationDate":"13/07/2019","address":"Bun Barat","email":"ddulwich12@hubpages.com","firstNameSpouse":"Dwayne","lastNameSpouse":"Heelis","identificationSpouse":"803885219","mobileSpouse":"958878440","relationShip":"Hijo","firstNameRelationShip":"Doralia","lastNameRelationShip":"Dulwich","mobileRelationShip":"8782256731","savingBalance":"1082","creditBalance":"518"},
{"id":"40","firstName":"Sansone","lastName":"Almak","identification":"9500824158","mobile":"950175202","secondMobile":"945940129","tariff":"Particular","civil":"Casado/a","birthDate":"09/06/2021","creationDate":"11/05/2021","address":"Palauig","email":"sbrusle13@acquirethisname.com","firstNameSpouse":"Anet","lastNameSpouse":"Wrist","identificationSpouse":"2054419543","mobileSpouse":"997955629","relationShip":"Padre","firstNameRelationShip":"Steve","lastNameRelationShip":"Brusle","mobileRelationShip":"7713107662","savingBalance":"497","creditBalance":"1198"},
{"id":"41","firstName":"Delmor","lastName":"McCloy","identification":"3540031397","mobile":"908739591","secondMobile":"974883763","tariff":"Particular","civil":"Casado/a","birthDate":"22/10/2021","creationDate":"01/10/2021","address":"Resende","email":"agoddman14@usa.gov","firstNameSpouse":"Reagan","lastNameSpouse":"Snary","identificationSpouse":"8983915561","mobileSpouse":"997516095","relationShip":"Prima","firstNameRelationShip":"Alexia","lastNameRelationShip":"Goddman","mobileRelationShip":"6460614329","savingBalance":"822","creditBalance":"2000"},
{"id":"42","firstName":"Mario","lastName":"Parcell","identification":"4431537063","mobile":"903077325","secondMobile":"926119854","tariff":"Particular","civil":"Casado/a","birthDate":"02/05/2021","creationDate":"07/11/2019","address":"Parion","email":"vrogge15@ocn.ne.jp","firstNameSpouse":"Yolanthe","lastNameSpouse":"Bellwood","identificationSpouse":"3801857147","mobileSpouse":"960538143","relationShip":"Hija","firstNameRelationShip":"Violante","lastNameRelationShip":"Rogge","mobileRelationShip":"9886607874","savingBalance":"563","creditBalance":"311"},
{"id":"43","firstName":"Laurena","lastName":"Cracker","identification":"5349869059","mobile":"990140081","secondMobile":"917677061","tariff":"Socio","civil":"Union Libre","birthDate":"08/04/2022","creationDate":"11/04/2020","address":"Corujeira","email":"nclooney16@arstechnica.com","firstNameSpouse":"Kass","lastNameSpouse":"Hallas","identificationSpouse":"6773564162","mobileSpouse":"929903842","relationShip":"Tao","firstNameRelationShip":"Nariko","lastNameRelationShip":"Clooney","mobileRelationShip":"7056789239","savingBalance":"69","creditBalance":"1239"}
,
{"id":"44","firstName":"Mariam","lastName":"Koch","identification":"1032570432","mobile":"901933425","secondMobile":"963124107","tariff":"Particular","civil":"Union Libre","birthDate":"07/04/2022","creationDate":"26/11/2020","address":"Zliv","email":"hmcwhan17@rediff.com","firstNameSpouse":"Wendi","lastNameSpouse":"Ethelstone","identificationSpouse":"5986711048","mobileSpouse":"990089845","relationShip":"Madre","firstNameRelationShip":"Hammad","lastNameRelationShip":"McWhan","mobileRelationShip":"340782818","savingBalance":"1468","creditBalance":"1682"}
,
{"id":"45","firstName":"Arlinda","lastName":"Merman","identification":"9178878728","mobile":"999660414","secondMobile":"949922009","tariff":"Particular","civil":"Union Libre","birthDate":"04/07/2021","creationDate":"30/08/2019","address":"Dortmund","email":"mpresdee18@spiegel.de","firstNameSpouse":"Billie","lastNameSpouse":"Stoyell","identificationSpouse":"5581368594","mobileSpouse":"998037171","relationShip":"Taa","firstNameRelationShip":"Monah","lastNameRelationShip":"Presdee","mobileRelationShip":"3288022987","savingBalance":"588","creditBalance":"791"}
,
{"id":"46","firstName":"Normand","lastName":"Jahn","identification":"2801012815","mobile":"923189948","secondMobile":"937912911","tariff":"Particular","civil":"Soltero/a","birthDate":"13/09/2021","creationDate":"19/04/2022","address":"Bishkek","email":"sbreadmore19@chronoengine.com","firstNameSpouse":"Cynthia","lastNameSpouse":"Brozsset","identificationSpouse":"1642698905","mobileSpouse":"968705934","relationShip":"Madre","firstNameRelationShip":"Sheilakathryn","lastNameRelationShip":"Breadmore","mobileRelationShip":"276419906","savingBalance":"1124","creditBalance":"1066"},
{"id":"47","firstName":"Desirae","lastName":"Looks","identification":"3309122649","mobile":"936501474","secondMobile":"991479256","tariff":"Socio","civil":"Viudo/a","birthDate":"07/02/2022","creationDate":"21/01/2021","address":"Babakandesa","email":"tfranzman1a@nps.gov","firstNameSpouse":"Haydon","lastNameSpouse":"Burtt","identificationSpouse":"8367647085","mobileSpouse":"922669019","relationShip":"Tao","firstNameRelationShip":"Teddy","lastNameRelationShip":"Franzman","mobileRelationShip":"1867101059","savingBalance":"457","creditBalance":"858"}
,
{"id":"48","firstName":"Tobe","lastName":"Pimbley","identification":"4031383337","mobile":"927353642","secondMobile":"902000177","tariff":"Particular","civil":"Union Libre","birthDate":"22/06/2021","creationDate":"06/05/2021","address":"Yanjiang","email":"rpawlicki1b@wix.com","firstNameSpouse":"Eddie","lastNameSpouse":"Pavyer","identificationSpouse":"7829440363","mobileSpouse":"964788356","relationShip":"Primo","firstNameRelationShip":"Rebekkah","lastNameRelationShip":"Pawlicki","mobileRelationShip":"4076884675","savingBalance":"1226","creditBalance":"465"}
,
{"id":"49","firstName":"Natividad","lastName":"Mistry","identification":"6661705018","mobile":"907457855","secondMobile":"984465238","tariff":"Particular","civil":"Soltero/a","birthDate":"18/04/2022","creationDate":"15/07/2020","address":"Cikiruh Wetan","email":"clafoy1c@gmpg.org","firstNameSpouse":"Ann-marie","lastNameSpouse":"Semken","identificationSpouse":"7592729801","mobileSpouse":"994194054","relationShip":"Amigo","firstNameRelationShip":"Cindee","lastNameRelationShip":"Lafoy","mobileRelationShip":"7676348308","savingBalance":"1008","creditBalance":"1054"},
{"id":"50","firstName":"Iseabal","lastName":"Easthope","identification":"3717083937","mobile":"975781467","secondMobile":"915835659","tariff":"Particular","civil":"Union Libre","birthDate":"03/11/2021","creationDate":"18/07/2019","address":"Aimin","email":"mspadoni1d@nationalgeographic.com","firstNameSpouse":"Byron","lastNameSpouse":"Colbourn","identificationSpouse":"5181253953","mobileSpouse":"949989847","relationShip":"Padre","firstNameRelationShip":"Maison","lastNameRelationShip":"Spadoni","mobileRelationShip":"307800191","savingBalance":"533","creditBalance":"1375"}
,
{"id":"51","firstName":"Verena","lastName":"MacInnes","identification":"8870884176","mobile":"953204450","secondMobile":"963984200","tariff":"Particular","civil":"Union Libre","birthDate":"22/06/2021","creationDate":"29/10/2019","address":"San Pedro Zacapa","email":"lwhitelaw1e@bloomberg.com","firstNameSpouse":"Xymenes","lastNameSpouse":"Pidgin","identificationSpouse":"2622072916","mobileSpouse":"969523328","relationShip":"Madre","firstNameRelationShip":"Lilian","lastNameRelationShip":"Whitelaw","mobileRelationShip":"2253656863","savingBalance":"1145","creditBalance":"1805"}
,
{"id":"52","firstName":"Becka","lastName":"Dodd","identification":"9681908939","mobile":"923356546","secondMobile":"993167059","tariff":"Particular","civil":"Viudo/a","birthDate":"18/09/2021","creationDate":"07/02/2022","address":"Luhansake","email":"eainsley1f@independent.co.uk","firstNameSpouse":"Emlyn","lastNameSpouse":"McCarl","identificationSpouse":"4970820112","mobileSpouse":"944823950","relationShip":"Tao","firstNameRelationShip":"Elisabetta","lastNameRelationShip":"Ainsley","mobileRelationShip":"3238855185","savingBalance":"383","creditBalance":"970"}
,
{"id":"53","firstName":"Cynthy","lastName":"La Wille","identification":"2413360821","mobile":"997536193","secondMobile":"917351213","tariff":"Socio","civil":"Soltero/a","birthDate":"15/09/2021","creationDate":"21/02/2022","address":"Ostrov","email":"hpitbladdo1g@state.gov","firstNameSpouse":"Sayers","lastNameSpouse":"Ruoff","identificationSpouse":"7550776931","mobileSpouse":"937685344","relationShip":"Taa","firstNameRelationShip":"Heloise","lastNameRelationShip":"Pitbladdo","mobileRelationShip":"4386541643","savingBalance":"623","creditBalance":"742"}
,
{"id":"54","firstName":"Marietta","lastName":"Warmington","identification":"104391325","mobile":"987098564","secondMobile":"963602511","tariff":"Particular","civil":"Soltero/a","birthDate":"18/05/2021","creationDate":"29/01/2021","address":"Kista","email":"ringall1h@unblog.fr","firstNameSpouse":"Kathleen","lastNameSpouse":"Glaister","identificationSpouse":"6190008488","mobileSpouse":"902068677","relationShip":"Amiga","firstNameRelationShip":"Rebecca","lastNameRelationShip":"Ingall","mobileRelationShip":"9950686807","savingBalance":"1744","creditBalance":"282"},
{"id":"55","firstName":"Sigrid","lastName":"Burtonshaw","identification":"9437848708","mobile":"918333419","secondMobile":"918463239","tariff":"Socio","civil":"Casado/a","birthDate":"03/01/2022","creationDate":"13/08/2020","address":"Lifuta","email":"alearned1i@unesco.org","firstNameSpouse":"Marigold","lastNameSpouse":"Ciccetti","identificationSpouse":"194429331","mobileSpouse":"976898247","relationShip":"Hija","firstNameRelationShip":"Allyn","lastNameRelationShip":"Learned","mobileRelationShip":"6068887400","savingBalance":"994","creditBalance":"811"},
{"id":"56","firstName":"Eugenio","lastName":"Ellse","identification":"8719796898","mobile":"942223679","secondMobile":"903211259","tariff":"Socio","civil":"Casado/a","birthDate":"24/10/2021","creationDate":"23/07/2019","address":"Llocllapampa","email":"gbevir1j@howstuffworks.com","firstNameSpouse":"Dena","lastNameSpouse":"Fiddy","identificationSpouse":"680422264","mobileSpouse":"912137080","relationShip":"Primo","firstNameRelationShip":"Gerda","lastNameRelationShip":"Bevir","mobileRelationShip":"5181343465","savingBalance":"463","creditBalance":"1643"},
{"id":"57","firstName":"Kain","lastName":"Pendock","identification":"7348492587","mobile":"968191007","secondMobile":"941559152","tariff":"Socio","civil":"Viudo/a","birthDate":"25/09/2021","creationDate":"13/10/2020","address":"Kawerau","email":"dmachan1k@mac.com","firstNameSpouse":"Janina","lastNameSpouse":"Rozsa","identificationSpouse":"1777222388","mobileSpouse":"969027193","relationShip":"Prima","firstNameRelationShip":"Dulcia","lastNameRelationShip":"Machan","mobileRelationShip":"4168508684","savingBalance":"1621","creditBalance":"287"},
{"id":"58","firstName":"Enrichetta","lastName":"Camamile","identification":"7059978407","mobile":"927917775","secondMobile":"948114164","tariff":"Socio","civil":"Soltero/a","birthDate":"17/01/2022","creationDate":"17/08/2020","address":"Landskrona","email":"tbecom1l@meetup.com","firstNameSpouse":"Oliviero","lastNameSpouse":"Lock","identificationSpouse":"3178444047","mobileSpouse":"945024407","relationShip":"Taa","firstNameRelationShip":"Tobin","lastNameRelationShip":"Becom","mobileRelationShip":"4722528976","savingBalance":"1174","creditBalance":"1362"}
,
{"id":"59","firstName":"Addy","lastName":"Sterke","identification":"9877371394","mobile":"922558786","secondMobile":"958399377","tariff":"Particular","civil":"Soltero/a","birthDate":"22/05/2021","creationDate":"25/06/2021","address":"Norrkaping","email":"csugar1m@reference.com","firstNameSpouse":"Saunderson","lastNameSpouse":"Puttan","identificationSpouse":"5048639","mobileSpouse":"943274223","relationShip":"Amiga","firstNameRelationShip":"Ceciley","lastNameRelationShip":"Sugar","mobileRelationShip":"6795505585","savingBalance":"1500","creditBalance":"497"}
,
{"id":"60","firstName":"Helena","lastName":"Ramsden","identification":"9062364860","mobile":"927609991","secondMobile":"979466257","tariff":"Particular","civil":"Casado/a","birthDate":"21/04/2021","creationDate":"26/06/2019","address":"Wotan","email":"ebrister1n@cocolog-nifty.com","firstNameSpouse":"Blaine","lastNameSpouse":"Alderton","identificationSpouse":"8456977671","mobileSpouse":"916775996","relationShip":"Amigo","firstNameRelationShip":"Ellsworth","lastNameRelationShip":"Brister","mobileRelationShip":"670413392","savingBalance":"477","creditBalance":"861"},
{"id":"61","firstName":"Allx","lastName":"Pressland","identification":"5457898601","mobile":"906409916","secondMobile":"919316562","tariff":"Particular","civil":"Casado/a","birthDate":"12/08/2021","creationDate":"07/10/2021","address":"Gio Linh","email":"dtreadgold1o@netlog.com","firstNameSpouse":"Tresa","lastNameSpouse":"Schukraft","identificationSpouse":"8788421268","mobileSpouse":"992133785","relationShip":"Madre","firstNameRelationShip":"Denys","lastNameRelationShip":"Treadgold","mobileRelationShip":"1170780490","savingBalance":"1209","creditBalance":"1964"},
{"id":"62","firstName":"Stacia","lastName":"Lowsely","identification":"9819512678","mobile":"974322509","secondMobile":"933657600","tariff":"Socio","civil":"Casado/a","birthDate":"04/05/2021","creationDate":"25/07/2021","address":"Jijiga","email":"diskowicz1p@noaa.gov","firstNameSpouse":"Yelena","lastNameSpouse":"Bellon","identificationSpouse":"7173246988","mobileSpouse":"977510339","relationShip":"Padre","firstNameRelationShip":"Danette","lastNameRelationShip":"Iskowicz","mobileRelationShip":"8245725428","savingBalance":"1529","creditBalance":"1296"},
{"id":"63","firstName":"Stephana","lastName":"Dutch","identification":"2749807882","mobile":"997363899","secondMobile":"922640827","tariff":"Particular","civil":"Soltero/a","birthDate":"14/01/2022","creationDate":"04/04/2022","address":"Qu?n Phu? Nhua?n","email":"bmacrow1q@elpais.com","firstNameSpouse":"Alys","lastNameSpouse":"Carding","identificationSpouse":"3629008619","mobileSpouse":"969584897","relationShip":"Hijo","firstNameRelationShip":"Brittni","lastNameRelationShip":"Macrow","mobileRelationShip":"7547153042","savingBalance":"1721","creditBalance":"1656"}
,
{"id":"64","firstName":"Mady","lastName":"Andrichak","identification":"8689265700","mobile":"915547675","secondMobile":"992629491","tariff":"Socio","civil":"Viudo/a","birthDate":"23/09/2021","creationDate":"29/10/2019","address":"Wielka Nieszawka","email":"kdominik1r@studiopress.com","firstNameSpouse":"Shandie","lastNameSpouse":"Kelcher","identificationSpouse":"4283190258","mobileSpouse":"971064465","relationShip":"Hijo","firstNameRelationShip":"Kellie","lastNameRelationShip":"Dominik","mobileRelationShip":"2421872630","savingBalance":"1963","creditBalance":"1203"},
{"id":"65","firstName":"Lonee","lastName":"McCluskey","identification":"5318306459","mobile":"985299603","secondMobile":"924114331","tariff":"Particular","civil":"Union Libre","birthDate":"12/07/2021","creationDate":"04/09/2021","address":"Jianqiao","email":"ajoist1s@networksolutions.com","firstNameSpouse":"Kasey","lastNameSpouse":"Pithie","identificationSpouse":"2683985797","mobileSpouse":"920667302","relationShip":"Amiga","firstNameRelationShip":"Arlyn","lastNameRelationShip":"Joist","mobileRelationShip":"3052600182","savingBalance":"1489","creditBalance":"1624"}
,
{"id":"66","firstName":"Duffie","lastName":"Lawleff","identification":"325758894","mobile":"950540847","secondMobile":"962671159","tariff":"Particular","civil":"Casado/a","birthDate":"10/11/2021","creationDate":"29/04/2020","address":"Rudna Ma?a","email":"fmacconachy1t@devhub.com","firstNameSpouse":"Nicolle","lastNameSpouse":"Philipp","identificationSpouse":"5695708872","mobileSpouse":"980866176","relationShip":"Hijo","firstNameRelationShip":"Flossi","lastNameRelationShip":"Macconachy","mobileRelationShip":"8980584092","savingBalance":"1956","creditBalance":"1967"},
{"id":"67","firstName":"Devlen","lastName":"Muller","identification":"5330845670","mobile":"938587281","secondMobile":"959384654","tariff":"Particular","civil":"Casado/a","birthDate":"26/04/2021","creationDate":"24/01/2021","address":"Reutov","email":"wbranca1u@ifeng.com","firstNameSpouse":"Goraud","lastNameSpouse":"Nanson","identificationSpouse":"8136229010","mobileSpouse":"975013633","relationShip":"Taa","firstNameRelationShip":"Wilburt","lastNameRelationShip":"Branca","mobileRelationShip":"1183049985","savingBalance":"1248","creditBalance":"1498"}
,
{"id":"68","firstName":"Knox","lastName":"Woodrow","identification":"6072047072","mobile":"953959204","secondMobile":"933100662","tariff":"Socio","civil":"Viudo/a","birthDate":"20/09/2021","creationDate":"08/12/2020","address":"Iwye","email":"bpentecust1v@dmoz.org","firstNameSpouse":"Harriet","lastNameSpouse":"Paprotny","identificationSpouse":"9210560468","mobileSpouse":"903557220","relationShip":"Hija","firstNameRelationShip":"Bartlet","lastNameRelationShip":"Pentecust","mobileRelationShip":"4984338356","savingBalance":"1952","creditBalance":"163"},
{"id":"69","firstName":"Cornie","lastName":"Coggon","identification":"4235060765","mobile":"957012442","secondMobile":"929650346","tariff":"Particular","civil":"Viudo/a","birthDate":"14/05/2021","creationDate":"08/06/2020","address":"La Union","email":"tbruun1w@w3.org","firstNameSpouse":"Rodger","lastNameSpouse":"Bozward","identificationSpouse":"8651190898","mobileSpouse":"991539642","relationShip":"Padre","firstNameRelationShip":"Titos","lastNameRelationShip":"Bruun","mobileRelationShip":"7179628492","savingBalance":"1983","creditBalance":"883"}
,
{"id":"70","firstName":"Francois","lastName":"Gawkes","identification":"7287993375","mobile":"903374480","secondMobile":"945108826","tariff":"Socio","civil":"Soltero/a","birthDate":"11/04/2022","creationDate":"15/03/2020","address":"Koronadal","email":"akollasch1x@ning.com","firstNameSpouse":"Andreas","lastNameSpouse":"Lackney","identificationSpouse":"2467960292","mobileSpouse":"918374691","relationShip":"Prima","firstNameRelationShip":"Alane","lastNameRelationShip":"Kollasch","mobileRelationShip":"6379429531","savingBalance":"681","creditBalance":"445"},
{"id":"71","firstName":"Madelin","lastName":"Phear","identification":"2221248644","mobile":"979874077","secondMobile":"967289866","tariff":"Socio","civil":"Union Libre","birthDate":"06/08/2021","creationDate":"30/04/2020","address":"Songhae","email":"mhaycroft1y@fotki.com","firstNameSpouse":"Zachary","lastNameSpouse":"Drinkel","identificationSpouse":"6559379368","mobileSpouse":"922721382","relationShip":"Prima","firstNameRelationShip":"Moshe","lastNameRelationShip":"Haycroft","mobileRelationShip":"1226030677","savingBalance":"110","creditBalance":"131"}
,
{"id":"72","firstName":"Kendall","lastName":"McClory","identification":"1835707698","mobile":"910063041","secondMobile":"908677553","tariff":"Particular","civil":"Casado/a","birthDate":"06/07/2021","creationDate":"11/06/2020","address":"Tefa","email":"jsummerlee1z@exblog.jp","firstNameSpouse":"Gage","lastNameSpouse":"Du Plantier","identificationSpouse":"6330939572","mobileSpouse":"966070579","relationShip":"Hijo","firstNameRelationShip":"Jamill","lastNameRelationShip":"Summerlee","mobileRelationShip":"1058147631","savingBalance":"910","creditBalance":"1815"}
,
{"id":"73","firstName":"Dixie","lastName":"Springford","identification":"3007086454","mobile":"910945147","secondMobile":"943741849","tariff":"Socio","civil":"Union Libre","birthDate":"06/12/2021","creationDate":"17/02/2022","address":"Siborong-borong","email":"hmccray20@latimes.com","firstNameSpouse":"Margarethe","lastNameSpouse":"Wolfendell","identificationSpouse":"2934863143","mobileSpouse":"949750568","relationShip":"Amigo","firstNameRelationShip":"Helga","lastNameRelationShip":"McCray","mobileRelationShip":"2519553652","savingBalance":"1025","creditBalance":"1972"}
,
{"id":"74","firstName":"Oliviero","lastName":"Manser","identification":"9070710894","mobile":"904437254","secondMobile":"916555646","tariff":"Socio","civil":"Soltero/a","birthDate":"07/07/2021","creationDate":"11/04/2022","address":"Yuracyacu","email":"kpolland21@loc.gov","firstNameSpouse":"Port","lastNameSpouse":"Liffe","identificationSpouse":"3324511792","mobileSpouse":"992525238","relationShip":"Taa","firstNameRelationShip":"Kristin","lastNameRelationShip":"Polland","mobileRelationShip":"2783098254","savingBalance":"879","creditBalance":"1099"}
,
{"id":"75","firstName":"Staffard","lastName":"Fake","identification":"7675237571","mobile":"939342856","secondMobile":"908755775","tariff":"Socio","civil":"Viudo/a","birthDate":"26/02/2022","creationDate":"24/09/2019","address":"Zhongshan","email":"njeremiah22@shutterfly.com","firstNameSpouse":"Wandis","lastNameSpouse":"Barnaclough","identificationSpouse":"3750258641","mobileSpouse":"907026037","relationShip":"Tao","firstNameRelationShip":"Ned","lastNameRelationShip":"Jeremiah","mobileRelationShip":"358657427","savingBalance":"97","creditBalance":"1022"}
,
{"id":"76","firstName":"Bayard","lastName":"Ridehalgh","identification":"6820709527","mobile":"948835786","secondMobile":"991312366","tariff":"Socio","civil":"Union Libre","birthDate":"10/05/2021","creationDate":"21/01/2022","address":"aAnjarah","email":"ideboo23@eepurl.com","firstNameSpouse":"Cheslie","lastNameSpouse":"Lansbury","identificationSpouse":"9397278071","mobileSpouse":"959352539","relationShip":"Hijo","firstNameRelationShip":"Itch","lastNameRelationShip":"Deboo","mobileRelationShip":"2422436459","savingBalance":"1596","creditBalance":"1856"}
,
{"id":"77","firstName":"Jaquenette","lastName":"Mechic","identification":"9274143085","mobile":"967456722","secondMobile":"920204880","tariff":"Socio","civil":"Casado/a","birthDate":"24/07/2021","creationDate":"04/08/2020","address":"Thiers","email":"jdran24@opensource.org","firstNameSpouse":"Keriann","lastNameSpouse":"Ties","identificationSpouse":"4724297816","mobileSpouse":"922045150","relationShip":"Hijo","firstNameRelationShip":"Jaime","lastNameRelationShip":"Dran","mobileRelationShip":"5719885846","savingBalance":"1478","creditBalance":"1446"},
{"id":"78","firstName":"Gretal","lastName":"Gare","identification":"8756230","mobile":"999655391","secondMobile":"980641896","tariff":"Socio","civil":"Soltero/a","birthDate":"13/08/2021","creationDate":"05/12/2019","address":"Sabaia","email":"velcome25@mail.ru","firstNameSpouse":"Marlo","lastNameSpouse":"Pimlett","identificationSpouse":"2021607222","mobileSpouse":"972402109","relationShip":"Primo","firstNameRelationShip":"Virge","lastNameRelationShip":"Elcome","mobileRelationShip":"5414632305","savingBalance":"77","creditBalance":"1729"}
,
{"id":"79","firstName":"Piotr","lastName":"Bibby","identification":"7795993848","mobile":"967362341","secondMobile":"960579838","tariff":"Socio","civil":"Viudo/a","birthDate":"23/10/2021","creationDate":"09/06/2021","address":"Campaka","email":"ggascoine26@t-online.de","firstNameSpouse":"Sherrie","lastNameSpouse":"Sleep","identificationSpouse":"5717799017","mobileSpouse":"903684916","relationShip":"Hijo","firstNameRelationShip":"Garrik","lastNameRelationShip":"Gascoine","mobileRelationShip":"3546262183","savingBalance":"116","creditBalance":"1354"},
{"id":"80","firstName":"Dyann","lastName":"Lamba","identification":"9263784431","mobile":"959041480","secondMobile":"930074419","tariff":"Socio","civil":"Union Libre","birthDate":"09/12/2021","creationDate":"26/02/2020","address":"Saboya","email":"aheatly27@ebay.co.uk","firstNameSpouse":"Daniella","lastNameSpouse":"Campaigne","identificationSpouse":"7658286248","mobileSpouse":"957052447","relationShip":"Primo","firstNameRelationShip":"Archibaldo","lastNameRelationShip":"Heatly","mobileRelationShip":"9560552989","savingBalance":"232","creditBalance":"1253"}
,
{"id":"81","firstName":"Anastasia","lastName":"Madsen","identification":"5196060763","mobile":"971046944","secondMobile":"962343346","tariff":"Socio","civil":"Soltero/a","birthDate":"10/06/2021","creationDate":"04/12/2020","address":"Bajo","email":"landresser28@blogtalkradio.com","firstNameSpouse":"Leyla","lastNameSpouse":"Lathleiffure","identificationSpouse":"4879952725","mobileSpouse":"974542389","relationShip":"Amigo","firstNameRelationShip":"Lettie","lastNameRelationShip":"Andresser","mobileRelationShip":"2764475235","savingBalance":"1634","creditBalance":"1276"},
{"id":"82","firstName":"Adara","lastName":"Behrend","identification":"4733305764","mobile":"939335174","secondMobile":"990339839","tariff":"Particular","civil":"Soltero/a","birthDate":"01/02/2022","creationDate":"17/12/2021","address":"Gaoping","email":"msoutherell29@psu.edu","firstNameSpouse":"Enrika","lastNameSpouse":"Beedie","identificationSpouse":"6660855943","mobileSpouse":"905179378","relationShip":"Amigo","firstNameRelationShip":"Meade","lastNameRelationShip":"Southerell","mobileRelationShip":"9386065295","savingBalance":"643","creditBalance":"1744"},
{"id":"83","firstName":"Marcile","lastName":"Demschke","identification":"5817812568","mobile":"928019549","secondMobile":"908440911","tariff":"Particular","civil":"Viudo/a","birthDate":"05/09/2021","creationDate":"05/02/2022","address":"Dalakovo","email":"msine2a@ucla.edu","firstNameSpouse":"Ruperta","lastNameSpouse":"Caltun","identificationSpouse":"9475516459","mobileSpouse":"922212127","relationShip":"Prima","firstNameRelationShip":"Margaretha","lastNameRelationShip":"Sine","mobileRelationShip":"4679719879","savingBalance":"680","creditBalance":"920"},
{"id":"84","firstName":"Worthington","lastName":"Byrnes","identification":"3635968174","mobile":"921451129","secondMobile":"940556981","tariff":"Particular","civil":"Casado/a","birthDate":"30/09/2021","creationDate":"06/02/2021","address":"Orlovskiy","email":"kguinan2b@networkadvertising.org","firstNameSpouse":"Aldin","lastNameSpouse":"Spracklin","identificationSpouse":"6174321783","mobileSpouse":"968608352","relationShip":"Taa","firstNameRelationShip":"Kacie","lastNameRelationShip":"Guinan","mobileRelationShip":"7849505631","savingBalance":"1687","creditBalance":"1417"}
,
{"id":"85","firstName":"Duffie","lastName":"Corsham","identification":"3470134791","mobile":"972118358","secondMobile":"958143418","tariff":"Particular","civil":"Soltero/a","birthDate":"08/12/2021","creationDate":"22/12/2020","address":"Vinnytsya","email":"kaldersey2c@nature.com","firstNameSpouse":"Gilberta","lastNameSpouse":"Mapledoram","identificationSpouse":"7522672773","mobileSpouse":"972663817","relationShip":"Madre","firstNameRelationShip":"Koren","lastNameRelationShip":"Aldersey","mobileRelationShip":"3025297736","savingBalance":"1453","creditBalance":"733"},
{"id":"86","firstName":"Charla","lastName":"Warr","identification":"4621227612","mobile":"950446741","secondMobile":"950338003","tariff":"Particular","civil":"Casado/a","birthDate":"06/09/2021","creationDate":"08/04/2022","address":"Kuala Lumpur","email":"abarlass2d@state.tx.us","firstNameSpouse":"Scarface","lastNameSpouse":"Ismay","identificationSpouse":"7269911965","mobileSpouse":"973463676","relationShip":"Hijo","firstNameRelationShip":"Adda","lastNameRelationShip":"Barlass","mobileRelationShip":"8241653935","savingBalance":"917","creditBalance":"1653"},
{"id":"87","firstName":"Vachel","lastName":"Ryal","identification":"7716752559","mobile":"986180109","secondMobile":"944503087","tariff":"Particular","civil":"Union Libre","birthDate":"16/01/2022","creationDate":"08/06/2019","address":"Talawi","email":"gyglesia2e@mit.edu","firstNameSpouse":"Garald","lastNameSpouse":"Jeeves","identificationSpouse":"2711960064","mobileSpouse":"990992601","relationShip":"Amigo","firstNameRelationShip":"Gilbert","lastNameRelationShip":"Yglesia","mobileRelationShip":"3270534332","savingBalance":"1517","creditBalance":"111"}
,
{"id":"88","firstName":"Eugenie","lastName":"Feehan","identification":"2718561098","mobile":"907373713","secondMobile":"959857837","tariff":"Particular","civil":"Soltero/a","birthDate":"18/01/2022","creationDate":"18/11/2021","address":"Banjar Budakeling","email":"gkeele2f@theguardian.com","firstNameSpouse":"Margarette","lastNameSpouse":"Klesl","identificationSpouse":"8676286715","mobileSpouse":"981368976","relationShip":"Padre","firstNameRelationShip":"Gerrilee","lastNameRelationShip":"Keele","mobileRelationShip":"7417006680","savingBalance":"1620","creditBalance":"684"},
{"id":"89","firstName":"Bernadine","lastName":"Horrod","identification":"1254915047","mobile":"952108379","secondMobile":"986192324","tariff":"Particular","civil":"Casado/a","birthDate":"30/05/2021","creationDate":"26/08/2019","address":"Zabruaany","email":"bgifford2g@noaa.gov","firstNameSpouse":"Taddeo","lastNameSpouse":"Delnevo","identificationSpouse":"1662910513","mobileSpouse":"922478396","relationShip":"Prima","firstNameRelationShip":"Bax","lastNameRelationShip":"Gifford","mobileRelationShip":"2158981839","savingBalance":"684","creditBalance":"1994"}
,
{"id":"90","firstName":"Panchito","lastName":"Poundford","identification":"3171738067","mobile":"953756142","secondMobile":"996844762","tariff":"Particular","civil":"Casado/a","birthDate":"03/04/2022","creationDate":"16/02/2021","address":"Bidikotak","email":"jhyslop2h@sina.com.cn","firstNameSpouse":"Floris","lastNameSpouse":"Yanshin","identificationSpouse":"2906920594","mobileSpouse":"906160673","relationShip":"Padre","firstNameRelationShip":"Jermain","lastNameRelationShip":"Hyslop","mobileRelationShip":"2942637801","savingBalance":"490","creditBalance":"762"},
{"id":"91","firstName":"Ricard","lastName":"Stanford","identification":"1724745085","mobile":"933338003","secondMobile":"953856829","tariff":"Particular","civil":"Union Libre","birthDate":"26/10/2021","creationDate":"09/06/2021","address":"Durazno","email":"shayer2i@yahoo.com","firstNameSpouse":"Constantine","lastNameSpouse":"Merritt","identificationSpouse":"2486507884","mobileSpouse":"944976749","relationShip":"Tao","firstNameRelationShip":"Skip","lastNameRelationShip":"Hayer","mobileRelationShip":"4098445852","savingBalance":"740","creditBalance":"72"}
,
{"id":"92","firstName":"Corliss","lastName":"Lantiff","identification":"3290071464","mobile":"936831988","secondMobile":"986739201","tariff":"Particular","civil":"Union Libre","birthDate":"26/03/2022","creationDate":"24/12/2021","address":"Gegu","email":"bladloe2j@vinaora.com","firstNameSpouse":"Dillie","lastNameSpouse":"Heymes","identificationSpouse":"4419630982","mobileSpouse":"972147105","relationShip":"Amigo","firstNameRelationShip":"Blane","lastNameRelationShip":"Ladloe","mobileRelationShip":"2118725739","savingBalance":"195","creditBalance":"540"}
,
{"id":"93","firstName":"Matty","lastName":"Pigeram","identification":"2254908858","mobile":"964331059","secondMobile":"996048874","tariff":"Particular","civil":"Soltero/a","birthDate":"30/04/2021","creationDate":"05/12/2021","address":"Tielu","email":"srobilart2k@microsoft.com","firstNameSpouse":"Nichol","lastNameSpouse":"Keighley","identificationSpouse":"1149981607","mobileSpouse":"961105480","relationShip":"Hija","firstNameRelationShip":"Sherri","lastNameRelationShip":"Robilart","mobileRelationShip":"8512308702","savingBalance":"909","creditBalance":"1772"},
{"id":"94","firstName":"Veronike","lastName":"Gallandre","identification":"1752474628","mobile":"906128514","secondMobile":"948223090","tariff":"Socio","civil":"Viudo/a","birthDate":"19/06/2021","creationDate":"23/07/2021","address":"Nanshan","email":"ccastellet2l@bloomberg.com","firstNameSpouse":"Walliw","lastNameSpouse":"Gilks","identificationSpouse":"2169790851","mobileSpouse":"983218795","relationShip":"Padre","firstNameRelationShip":"Cris","lastNameRelationShip":"Castellet","mobileRelationShip":"9329614494","savingBalance":"1992","creditBalance":"1931"},
{"id":"95","firstName":"Elise","lastName":"Fontin","identification":"6682706544","mobile":"973932704","secondMobile":"985011975","tariff":"Particular","civil":"Soltero/a","birthDate":"31/10/2021","creationDate":"26/06/2021","address":"Houston","email":"pewing2m@economist.com","firstNameSpouse":"Antoine","lastNameSpouse":"Tankus","identificationSpouse":"913249517","mobileSpouse":"979950313","relationShip":"Amigo","firstNameRelationShip":"Pete","lastNameRelationShip":"Ewing","mobileRelationShip":"6773250271","savingBalance":"372","creditBalance":"917"},
{"id":"96","firstName":"Conan","lastName":"Byway","identification":"741732695","mobile":"987587689","secondMobile":"934635487","tariff":"Socio","civil":"Soltero/a","birthDate":"14/08/2021","creationDate":"12/03/2021","address":"Aborlan","email":"sclampe2n@mapquest.com","firstNameSpouse":"Damita","lastNameSpouse":"Brunon","identificationSpouse":"1848453808","mobileSpouse":"997097176","relationShip":"Padre","firstNameRelationShip":"Selie","lastNameRelationShip":"Clampe","mobileRelationShip":"8015454458","savingBalance":"68","creditBalance":"159"},
{"id":"97","firstName":"Malva","lastName":"Giblin","identification":"3294555313","mobile":"923485590","secondMobile":"948246795","tariff":"Socio","civil":"Soltero/a","birthDate":"18/11/2021","creationDate":"27/01/2022","address":"Shanglu","email":"rwhitlock2o@discovery.com","firstNameSpouse":"Lonnie","lastNameSpouse":"Waugh","identificationSpouse":"3792876295","mobileSpouse":"934458273","relationShip":"Hija","firstNameRelationShip":"Raddy","lastNameRelationShip":"Whitlock","mobileRelationShip":"5629598666","savingBalance":"358","creditBalance":"1804"},
{"id":"98","firstName":"Yolanda","lastName":"Radolf","identification":"1792436301","mobile":"931503566","secondMobile":"992802805","tariff":"Particular","civil":"Viudo/a","birthDate":"18/12/2021","creationDate":"27/06/2020","address":"Utkivka","email":"tcoleman2p@buzzfeed.com","firstNameSpouse":"Rafe","lastNameSpouse":"Miles","identificationSpouse":"2260269055","mobileSpouse":"927872408","relationShip":"Amigo","firstNameRelationShip":"Tony","lastNameRelationShip":"Coleman","mobileRelationShip":"9703723653","savingBalance":"508","creditBalance":"899"},
{"id":"99","firstName":"Benedicta","lastName":"Candey","identification":"2414727158","mobile":"939090702","secondMobile":"954987040","tariff":"Socio","civil":"Viudo/a","birthDate":"21/11/2021","creationDate":"13/02/2022","address":"Milicz","email":"cdedney2q@imdb.com","firstNameSpouse":"Fidelity","lastNameSpouse":"Wonfar","identificationSpouse":"6176164114","mobileSpouse":"944080139","relationShip":"Amigo","firstNameRelationShip":"Candide","lastNameRelationShip":"Dedney","mobileRelationShip":"3501683909","savingBalance":"1460","creditBalance":"1217"},
{"id":"100","firstName":"Arley","lastName":"Cunney","identification":"7877259998","mobile":"988897626","secondMobile":"986718338","tariff":"Socio","civil":"Soltero/a","birthDate":"13/02/2022","creationDate":"17/04/2020","address":"Wu?ahp?r","email":"tgellion2r@flickr.com","firstNameSpouse":"Chris","lastNameSpouse":"De Michetti","identificationSpouse":"4315127149","mobileSpouse":"948196117","relationShip":"Madre","firstNameRelationShip":"Tine","lastNameRelationShip":"Gellion","mobileRelationShip":"1164154802","savingBalance":"697","creditBalance":"1748"}
]
